puree/__init__.py
puree/compiler.py
puree/extract_images.py
puree/extract_text.py
puree/extract_text_input.py
puree/hit_op.py
puree/hot_reload.py
puree/hot_reload_ops.py
puree/img_op.py
puree/mouse_op.py
puree/native_bindings.py
puree/panel.py
puree/parser.py
puree/parser_op.py
puree/render.py
puree/scroll_op.py
puree/space_config.py
puree/text_input_op.py
puree/text_op.py
puree/utils.py
puree/components/__init__.py
puree/components/container.py
puree/components/style.py
puree/native_binaries/puree_rust_core.pyd
puree/shaders/container.glsl
puree/shaders/fragment.glsl
puree/shaders/outline.glsl
puree/shaders/vertex.glsl
puree_ui-0.1.3.dist-info/LICENSE
puree_ui-0.1.3.dist-info/METADATA
puree_ui-0.1.3.dist-info/WHEEL
puree_ui-0.1.3.dist-info/top_level.txt
puree_ui-0.1.3.dist-info/RECORD
