Metadata-Version: 2.2
Name: puree-ui
Version: 0.1.3
Summary: XWZ Puree UI framework for Blender
Home-page: https://github.com/nicolaiprodromov/puree
Author: Nicolai Prodromov
License: MIT
Project-URL: Homepage, https://github.com/nicolaiprodromov/puree
Project-URL: Repository, https://github.com/nicolaiprodromov/puree
Classifier: Development Status :: 3 - Alpha
Classifier: Intended Audience :: Developers
Classifier: Topic :: Software Development :: User Interfaces
Classifier: License :: OSI Approved :: MIT License
Classifier: Programming Language :: Python :: 3
Classifier: Programming Language :: Python :: 3.11
Requires-Python: >=3.11
License-File: LICENSE
Requires-Dist: moderngl==5.12.0
Requires-Dist: glcontext==3.0.0
Requires-Dist: stretchable==1.1.7
Requires-Dist: PyYAML==6.0.2
Requires-Dist: typing-extensions==4.15.0
Requires-Dist: attrs==25.3.0
Dynamic: home-page
Dynamic: requires-python
